HPC_GA/__init__.py
HPC_GA/common/__init__.py
HPC_GA/common/chromosome.py
HPC_GA/common/population.py
HPC_GA/core/__init__.py
HPC_GA/core/genetic_algorithm.py
HPC_GA/core/operators.py
HPC_GA/parallel/__init__.py
HPC_GA/parallel/parallel_ga.py
HPC_GA/parallel/utils.py
HPC_GA/utils/__init__.py
HPC_GA/utils/fitness.py
HPC_GA/utils/visualization.py
hpc_ga-0.2.26.dist-info/licenses/LICENSE.txt
hpc_ga-0.2.26.dist-info/METADATA
hpc_ga-0.2.26.dist-info/WHEEL
hpc_ga-0.2.26.dist-info/top_level.txt
hpc_ga-0.2.26.dist-info/RECORD
