Metadata-Version: 2.4
Name: hpc-ga
Version: 0.2.26
Summary: High Performance Computing Genetic Algorithm Framework
Author-email: KEFSI Nourhane <nourhanekefsi@gmail.com>
License-Expression: MIT
Project-URL: Homepage, https://github.com/nourhanekefsi/Master_final_project/tree/main/src/Frameworks/HPC_GA
Classifier: Programming Language :: Python :: 3
Classifier: Operating System :: OS Independent
Requires-Python: >=3.8
License-File: LICENSE.txt
Requires-Dist: numpy>=1.21.0
Requires-Dist: networkx>=3.0
Requires-Dist: ray>=2.0
Dynamic: license-file
